odoo/addons/maintenance_project/README.rst
odoo/addons/maintenance_project/__init__.py
odoo/addons/maintenance_project/__manifest__.py
odoo/addons/maintenance_project/data/demo_maintenance_project.xml
odoo/addons/maintenance_project/i18n/es.po
odoo/addons/maintenance_project/i18n/it.po
odoo/addons/maintenance_project/i18n/maintenance_project.pot
odoo/addons/maintenance_project/models/__init__.py
odoo/addons/maintenance_project/models/maintenance_equipment.py
odoo/addons/maintenance_project/models/maintenance_request.py
odoo/addons/maintenance_project/models/project_project.py
odoo/addons/maintenance_project/readme/CONTRIBUTORS.rst
odoo/addons/maintenance_project/readme/DESCRIPTION.rst
odoo/addons/maintenance_project/report/maintenance_request_report.xml
odoo/addons/maintenance_project/security/maintenance_project_security.xml
odoo/addons/maintenance_project/static/description/icon.png
odoo/addons/maintenance_project/static/description/index.html
odoo/addons/maintenance_project/tests/__init__.py
odoo/addons/maintenance_project/tests/test_maintenance_project.py
odoo/addons/maintenance_project/views/maintenance_equipment_views.xml
odoo/addons/maintenance_project/views/maintenance_request_views.xml
odoo/addons/maintenance_project/views/project_project_views.xml
odoo14_addon_maintenance_project-14.0.1.1.2.dist-info/METADATA
odoo14_addon_maintenance_project-14.0.1.1.2.dist-info/WHEEL
odoo14_addon_maintenance_project-14.0.1.1.2.dist-info/top_level.txt
odoo14_addon_maintenance_project-14.0.1.1.2.dist-info/RECORD
