Metadata-Version: 2.1
Name: odoo14-addon-maintenance-project
Version: 14.0.1.1.2
Summary: Adds projects to maintenance equipments and requests
Home-page: https://github.com/OCA/maintenance
Author: Odoo Community Association (OCA), Solvos
Author-email: support@odoo-community.org
License: AGPL-3
Platform: UNKNOWN
Classifier: Programming Language :: Python
Classifier: Framework :: Odoo
Classifier: Framework :: Odoo :: 14.0
Classifier: License :: OSI Approved :: GNU Affero General Public License v3
Requires-Python: >=3.6
Requires-Dist: odoo14-addon-base-maintenance
Requires-Dist: odoo <14.1dev,>=14.0a
